MarkupPy/__init__.py
MarkupPy/markup.py
markuppy-1.16.dist-info/LICENSE
markuppy-1.16.dist-info/METADATA
markuppy-1.16.dist-info/WHEEL
markuppy-1.16.dist-info/top_level.txt
markuppy-1.16.dist-info/RECORD
