Metadata-Version: 2.2
Name: MarkupPy
Version: 1.16
Summary: An HTML/XML generator
Home-page: https://github.com/tylerbakke/MarkupPy
Author: Daniel Nogradi
Author-email: Daniel Nogradi <nogradi@gmail.com>
Maintainer-email: Tyler Bakke <tylerbakke@gmail.com>
License: MIT
Project-URL: Homepage, https://github.com/tylerbakke/MarkupPy
Project-URL: Documentation, https://tylerbakke.github.io/MarkupPy/
Project-URL: Bug Tracker, https://github.com/tylerbakke/MarkupPy/issues
Classifier: Environment :: Console
Classifier: Programming Language :: Python :: 2
Classifier: Programming Language :: Python :: 3
Classifier: License :: OSI Approved :: MIT License
Classifier: Topic :: Software Development :: Libraries :: Python Modules
Classifier: Topic :: Text Processing :: Markup :: HTML
Classifier: Topic :: Text Processing :: Markup :: XML
Requires-Python: >=2.7
License-File: LICENSE
Dynamic: author
Dynamic: home-page
